LICENSE.txt
README.md
setup.cfg
setup.py
lztmarketapi/__init__.py
lztmarketapi.egg-info/PKG-INFO
lztmarketapi.egg-info/SOURCES.txt
lztmarketapi.egg-info/dependency_links.txt
lztmarketapi.egg-info/requires.txt
lztmarketapi.egg-info/top_level.txt
lztmarketapi/ApiWrapper/ApiExceptions.py
lztmarketapi/ApiWrapper/__init__.py
lztmarketapi/Client/__init__.py
lztmarketapi/Client/Games/__init__.py
lztmarketapi/Client/Games/GamesModels/BaseGame.py
lztmarketapi/Client/Games/GamesModels/Battlenet.py
lztmarketapi/Client/Games/GamesModels/Blitz.py
lztmarketapi/Client/Games/GamesModels/Cinema.py
lztmarketapi/Client/Games/GamesModels/Discord.py
lztmarketapi/Client/Games/GamesModels/EpicGames.py
lztmarketapi/Client/Games/GamesModels/EscapeFromTarkov.py
lztmarketapi/Client/Games/GamesModels/Fortnite.py
lztmarketapi/Client/Games/GamesModels/GenshinImpact.py
lztmarketapi/Client/Games/GamesModels/Instagram.py
lztmarketapi/Client/Games/GamesModels/Origin.py
lztmarketapi/Client/Games/GamesModels/SocialClub.py
lztmarketapi/Client/Games/GamesModels/Spotify.py
lztmarketapi/Client/Games/GamesModels/Steam.py
lztmarketapi/Client/Games/GamesModels/Supercell.py
lztmarketapi/Client/Games/GamesModels/Telegram.py
lztmarketapi/Client/Games/GamesModels/TikTok.py
lztmarketapi/Client/Games/GamesModels/Uplay.py
lztmarketapi/Client/Games/GamesModels/VK.py
lztmarketapi/Client/Games/GamesModels/VPN.py
lztmarketapi/Client/Games/GamesModels/Valorant.py
lztmarketapi/Client/Games/GamesModels/WarThunder.py
lztmarketapi/Client/Games/GamesModels/Warface.py
lztmarketapi/Client/Games/GamesModels/WorldOfTanks.py
lztmarketapi/Client/Games/GamesModels/YouTube.py
lztmarketapi/Client/Games/GamesModels/__init__.py
lztmarketapi/Client/Good/__init__.py
lztmarketapi/Client/Me/__init__.py
lztmarketapi/Client/Payment/__init__.py
lztmarketapi/Types/Category.py
lztmarketapi/Types/Currency.py
lztmarketapi/Types/Good.py
lztmarketapi/Types/Guarantee.py
lztmarketapi/Types/ItemOrigin.py
lztmarketapi/Types/Mail.py
lztmarketapi/Types/PaymentType.py
lztmarketapi/Types/Profile.py
lztmarketapi/Types/Result.py
lztmarketapi/Types/TimeValues.py
lztmarketapi/Types/User.py
lztmarketapi/Types/__init__.py
